hindsight_client/__init__.py
hindsight_client/hindsight_client.py
hindsight_client_api/__init__.py
hindsight_client_api/api_client.py
hindsight_client_api/api_response.py
hindsight_client_api/configuration.py
hindsight_client_api/exceptions.py
hindsight_client_api/rest.py
hindsight_client_api/api/__init__.py
hindsight_client_api/api/banks_api.py
hindsight_client_api/api/directives_api.py
hindsight_client_api/api/documents_api.py
hindsight_client_api/api/entities_api.py
hindsight_client_api/api/memory_api.py
hindsight_client_api/api/mental_models_api.py
hindsight_client_api/api/monitoring_api.py
hindsight_client_api/api/operations_api.py
hindsight_client_api/models/__init__.py
hindsight_client_api/models/add_background_request.py
hindsight_client_api/models/async_operation_submit_response.py
hindsight_client_api/models/background_response.py
hindsight_client_api/models/bank_list_item.py
hindsight_client_api/models/bank_list_response.py
hindsight_client_api/models/bank_profile_response.py
hindsight_client_api/models/bank_stats_response.py
hindsight_client_api/models/budget.py
hindsight_client_api/models/cancel_operation_response.py
hindsight_client_api/models/chunk_data.py
hindsight_client_api/models/chunk_include_options.py
hindsight_client_api/models/chunk_response.py
hindsight_client_api/models/consolidation_response.py
hindsight_client_api/models/create_bank_request.py
hindsight_client_api/models/create_directive_request.py
hindsight_client_api/models/create_mental_model_request.py
hindsight_client_api/models/create_mental_model_response.py
hindsight_client_api/models/delete_document_response.py
hindsight_client_api/models/delete_response.py
hindsight_client_api/models/directive_list_response.py
hindsight_client_api/models/directive_response.py
hindsight_client_api/models/disposition_traits.py
hindsight_client_api/models/document_response.py
hindsight_client_api/models/entity_detail_response.py
hindsight_client_api/models/entity_include_options.py
hindsight_client-0.4.7.dist-info/METADATA
hindsight_client-0.4.7.dist-info/WHEEL
hindsight_client-0.4.7.dist-info/RECORD
