Metadata-Version: 2.4
Name: hindsight-client
Version: 0.4.7
Summary: Python client for Hindsight - Semantic memory system with personality-driven thinking
Author: Hindsight Team
Requires-Python: >=3.10
Requires-Dist: aiohttp-retry>=2.8.3
Requires-Dist: aiohttp>=3.8.4
Requires-Dist: pydantic>=2
Requires-Dist: python-dateutil>=2.8.2
Requires-Dist: typing-extensions>=4.7.1
Requires-Dist: urllib3<3.0.0,>=2.1.0
Provides-Extra: test
Requires-Dist: pytest-asyncio>=0.21.0; extra == 'test'
Requires-Dist: pytest>=7.0.0; extra == 'test'
Requires-Dist: requests>=2.28.0; extra == 'test'
